README.md
setup.py
PowerPigeon.egg-info/PKG-INFO
PowerPigeon.egg-info/SOURCES.txt
PowerPigeon.egg-info/dependency_links.txt
PowerPigeon.egg-info/requires.txt
PowerPigeon.egg-info/top_level.txt
powerpigeon/__init__.py
powerpigeon/attributes.py
powerpigeon/exceptions.py
powerpigeon/index.py
powerpigeon/model.py