Metadata-Version: 1.0
Name: PowerPigeon
Version: 0.1.1
Summary: PowerPigeon is a model-based RethinkDB handler.
Home-page: https://github.com/JakeMakesStuff/PowerPigeon
Author: Jake Gealer
Author-email: jake@gealer.email
License: MPL-2.0
Platform: UNKNOWN
